[{"inputs": [], "stateMutability": "payable", "type": "constructor"}, {"anonymous": false, "inputs": [{"indexed": true, "internalType": "address", "name": "owner", "type": "address"}, {"indexed": true, "internalType": "address", "name": "spender", "type": "address"}, {"indexed": false, "internalType": "uint256", "name": "value", "type": "uint256"}], "name": "Approval", "type": "event"}, {"anonymous": false, "inputs": [{"indexed": true, "internalType": "address", "name": "previousOwner", "type": "address"}, {"indexed": true, "internalType": "address", "name": "newOwner", "type": "address"}], "name": "OwnershipTransferred", "type": "event"}, {"anonymous": false, "inputs": [{"indexed": true, "internalType": "address", "name": "from", "type": "address"}, {"indexed": true, "internalType": "address", "name": "to", "type": "address"}, {"indexed": false, "internalType": "uint256", "name": "value", "type": "uint256"}], "name": "Transfer", "type": "event"}, {"inputs": [{"internalType": "address", "name": "owner", "type": "address"}, {"internalType": "address", "name": "spender", "type": "address"}], "name": "allowance", "outputs": [{"internalType": "uint256", "name": "", "type": "uint256"}], "stateMutability": "view", "type": "function"}, {"inputs": [{"internalType": "address", "name": "spender", "type": "address"}, {"internalType": "uint256", "name": "amount", "type": "uint256"}], "name": "approve", "outputs": [{"internalType": "bool", "name": "", "type": "bool"}], "stateMutability": "nonpayable", "type": "function"}, {"inputs": [{"internalType": "address", "name": "account", "type": "address"}], "name": "balanceOf", "outputs": [{"internalType": "uint256", "name": "", "type": "uint256"}], "stateMutability": "view", "type": "function"}, {"inputs": [], "name": "buyTaxes", "outputs": [{"internalType": "uint32", "name": "liquidity", "type": "uint32"}, {"internalType": "uint32", "name": "marketing", "type": "uint32"}, {"internalType": "uint32", "name": "utility", "type": "uint32"}, {"internalType": "uint32", "name": "team", "type": "uint32"}], "stateMutability": "view", "type": "function"}, {"inputs": [], "name": "config", "outputs": [{"internalType": "uint256", "name": "numTokensSellToSwap", "type": "uint256"}, {"internalType": "uint256", "name": "maxWalletSize", "type": "uint256"}], "stateMutability": "view", "type": "function"}, {"inputs": [], "name": "decimals", "outputs": [{"internalType": "uint8", "name": "", "type": "uint8"}], "stateMutability": "pure", "type": "function"}, {"inputs": [], "name": "disableLimt", "outputs": [], "stateMutability": "nonpayable", "type": "function"}, {"inputs": [{"internalType": "address", "name": "account", "type": "address"}], "name": "excludeFromFee", "outputs": [], "stateMutability": "nonpayable", "type": "function"}, {"inputs": [{"internalType": "address", "name": "account", "type": "address"}], "name": "excludeInMaxWallet", "outputs": [], "stateMutability": "nonpayable", "type": "function"}, {"inputs": [{"internalType": "address", "name": "account", "type": "address"}], "name": "includeInFee", "outputs": [], "stateMutability": "nonpayable", "type": "function"}, {"inputs": [{"internalType": "address", "name": "account", "type": "address"}], "name": "includeInMaxWallet", "outputs": [], "stateMutability": "nonpayable", "type": "function"}, {"inputs": [{"internalType": "address", "name": "account", "type": "address"}], "name": "isExcludedFromFee", "outputs": [{"internalType": "bool", "name": "", "type": "bool"}], "stateMutability": "view", "type": "function"}, {"inputs": [{"internalType": "address", "name": "account", "type": "address"}], "name": "isExcludedFromMaxWallet", "outputs": [{"internalType": "bool", "name": "", "type": "bool"}], "stateMutability": "view", "type": "function"}, {"inputs": [{"internalType": "uint256", "name": "amountPercentage", "type": "uint256"}], "name": "manualETH", "outputs": [], "stateMutability": "nonpayable", "type": "function"}, {"inputs": [], "name": "manualToken", "outputs": [], "stateMutability": "nonpayable", "type": "function"}, {"inputs": [], "name": "name", "outputs": [{"internalType": "string", "name": "", "type": "string"}], "stateMutability": "pure", "type": "function"}, {"inputs": [], "name": "owner", "outputs": [{"internalType": "address", "name": "", "type": "address"}], "stateMutability": "view", "type": "function"}, {"inputs": [], "name": "renounceOwnership", "outputs": [], "stateMutability": "nonpayable", "type": "function"}, {"inputs": [], "name": "sellTaxes", "outputs": [{"internalType": "uint32", "name": "liquidity", "type": "uint32"}, {"internalType": "uint32", "name": "marketing", "type": "uint32"}, {"internalType": "uint32", "name": "utility", "type": "uint32"}, {"internalType": "uint32", "name": "team", "type": "uint32"}], "stateMutability": "view", "type": "function"}, {"inputs": [{"internalType": "uint32", "name": "liquidity", "type": "uint32"}, {"internalType": "uint32", "name": "marketing", "type": "uint32"}, {"internalType": "uint32", "name": "utility", "type": "uint32"}, {"internalType": "uint32", "name": "team", "type": "uint32"}], "name": "setBuyTaxes", "outputs": [], "stateMutability": "nonpayable", "type": "function"}, {"inputs": [{"internalType": "uint256", "name": "amount", "type": "uint256"}], "name": "setMaxWallet", "outputs": [], "stateMutability": "nonpayable", "type": "function"}, {"inputs": [{"internalType": "uint32", "name": "liquidity", "type": "uint32"}, {"internalType": "uint32", "name": "marketing", "type": "uint32"}, {"internalType": "uint32", "name": "utility", "type": "uint32"}, {"internalType": "uint32", "name": "team", "type": "uint32"}], "name": "setSellTaxes", "outputs": [], "stateMutability": "nonpayable", "type": "function"}, {"inputs": [{"internalType": "bool", "name": "_enabled", "type": "bool"}, {"internalType": "uint32", "name": "amount", "type": "uint32"}], "name": "setSwapValue", "outputs": [], "stateMutability": "nonpayable", "type": "function"}, {"inputs": [], "name": "settings", "outputs": [{"internalType": "bool", "name": "swapAndLiquifyEnabled", "type": "bool"}], "stateMutability": "view", "type": "function"}, {"inputs": [], "name": "symbol", "outputs": [{"internalType": "string", "name": "", "type": "string"}], "stateMutability": "pure", "type": "function"}, {"inputs": [], "name": "totalSupply", "outputs": [{"internalType": "uint256", "name": "", "type": "uint256"}], "stateMutability": "pure", "type": "function"}, {"inputs": [{"internalType": "address", "name": "recipient", "type": "address"}, {"internalType": "uint256", "name": "amount", "type": "uint256"}], "name": "transfer", "outputs": [{"internalType": "bool", "name": "", "type": "bool"}], "stateMutability": "nonpayable", "type": "function"}, {"inputs": [{"internalType": "address", "name": "sender", "type": "address"}, {"internalType": "address", "name": "recipient", "type": "address"}, {"internalType": "uint256", "name": "amount", "type": "uint256"}], "name": "transferFrom", "outputs": [{"internalType": "bool", "name": "", "type": "bool"}], "stateMutability": "nonpayable", "type": "function"}, {"inputs": [{"internalType": "address", "name": "newOwner", "type": "address"}], "name": "transferOwnership", "outputs": [], "stateMutability": "nonpayable", "type": "function"}, {"inputs": [], "name": "uniswapV2Pair", "outputs": [{"internalType": "address", "name": "", "type": "address"}], "stateMutability": "view", "type": "function"}, {"inputs": [], "name": "uniswapV2Router", "outputs": [{"internalType": "contract IUniswapV2Router02", "name": "", "type": "address"}], "stateMutability": "view", "type": "function"}, {"inputs": [{"internalType": "address payable", "name": "marketingWallet", "type": "address"}, {"internalType": "address payable", "name": "utilityWallet", "type": "address"}, {"internalType": "address payable", "name": "teamAWallet", "type": "address"}], "name": "updateWallets", "outputs": [], "stateMutability": "nonpayable", "type": "function"}, {"inputs": [], "name": "wallets", "outputs": [{"internalType": "address payable", "name": "marketingWallet", "type": "address"}, {"internalType": "address payable", "name": "utilityWallet", "type": "address"}, {"internalType": "address payable", "name": "teamWallet", "type": "address"}], "stateMutability": "view", "type": "function"}, {"stateMutability": "payable", "type": "receive"}]